README.md
setup.py
cryptokit/__init__.py
cryptokit/aes.py
cryptokit/csr.py
cryptokit/dh.py
cryptokit/ecc.py
cryptokit/ed25519.py
cryptokit/exception.py
cryptokit/otp.py
cryptokit/rsa.py
cryptokit/utils.py
cryptokit.egg-info/PKG-INFO
cryptokit.egg-info/SOURCES.txt
cryptokit.egg-info/dependency_links.txt
cryptokit.egg-info/not-zip-safe
cryptokit.egg-info/requires.txt
cryptokit.egg-info/top_level.txt
tests/__init__.py
tests/test_aes.py
tests/test_csr.py
tests/test_rsa.py
tests/test_utils.py