Metadata-Version: 1.0
Name: cryptokit
Version: 0.0.9
Summary: cryptokit is a cryptography kit base on pyca Cryptography.
Home-page: https://github.com/istommao/cryptokit
Author: silence
Author-email: istommao@gmail.com
License: UNKNOWN
Keywords: cryptokit is a cryptography kit base on pyca Cryptography!
Platform: UNKNOWN
